vault_fix/__init__.py
vault_fix/__main__.py
vault_fix/_log.py
vault_fix/dump.py
vault_fix/load.py
vault_fix/_crypto/__init__.py
vault_fix/_crypto/constants.py
vault_fix/_crypto/message.py
vault_fix/_crypto/symmetric.py
vault_fix/serializers/__init__.py
vault_fix/serializers/json.py
vault_fix/serializers/yaml.py
vault_fix-1.4.0.dist-info/METADATA
vault_fix-1.4.0.dist-info/WHEEL
vault_fix-1.4.0.dist-info/entry_points.txt
vault_fix-1.4.0.dist-info/licenses/LICENSE.txt
vault_fix-1.4.0.dist-info/RECORD
