Metadata-Version: 2.3
Name: vault-fix
Version: 1.4.0
Summary: Tool for importing and exporting vault fixture files to and from vault dev mode instances.
Project-URL: Homepage, https://github.com/SnijderC/vault-fixtures
Author-email: Chris Snijder <github@chrissnijder.nl>
License: Copyright 2023 Chris Snijder
License-File: LICENSE.txt
Keywords: fixture,hasicorp,migration,testing,vault
Classifier: Development Status :: 5 - Production/Stable
Classifier: Environment :: Console
Classifier: Intended Audience :: Developers
Classifier: License :: OSI Approved :: Apache Software License
Classifier: Operating System :: MacOS
Classifier: Operating System :: POSIX :: Linux
Classifier: Programming Language :: Python
Classifier: Programming Language :: Python :: 3 :: Only
Classifier: Programming Language :: Python :: 3.9
Classifier: Programming Language :: Python :: 3.10
Classifier: Programming Language :: Python :: 3.11
Requires-Python: >=3.9
Requires-Dist: cryptography>=42.0.5
Requires-Dist: hvac>=0.10.11
Requires-Dist: pyyaml>=6.0
Requires-Dist: rich>=13.5.2
Requires-Dist: typer[all]>=0.9.0
Provides-Extra: dev
Requires-Dist: coverage>=7.4.4; extra == 'dev'
Requires-Dist: hatch>=1.7.0; extra == 'dev'
Requires-Dist: pip-tools>=7.1.0; extra == 'dev'
Requires-Dist: pytest-asyncio>=0.23.6; extra == 'dev'
Requires-Dist: pytest-cov>=5.0.0; extra == 'dev'
Requires-Dist: pytest-random-order>=1.1.1; extra == 'dev'
Requires-Dist: pytest>=8.1.1; extra == 'dev'
